graphql_api/__init__.py
graphql_api/server.py
2112_generator_graphql_api-0.0.1.dist-info/METADATA
2112_generator_graphql_api-0.0.1.dist-info/WHEEL
2112_generator_graphql_api-0.0.1.dist-info/top_level.txt
2112_generator_graphql_api-0.0.1.dist-info/RECORD
