Metadata-Version: 2.1
Name: 2112_generator_graphql_api
Version: 0.0.1
Summary: GraphQL API Python Client
Home-page: https://github.com/Elbujito/2112
Author: Elbujito
Author-email: adrien.roques.31@outlook.fr
Classifier: Programming Language :: Python :: 3
Classifier: License :: OSI Approved :: MIT License
Classifier: Operating System :: OS Independent
Requires-Python: >=3.6
Requires-Dist: graphql-core==3.2.3
Requires-Dist: fastapi
Requires-Dist: uvicorn
